trends/__init__.py
trends/docs/Makefile
trends/docs/source/api.rst
trends/docs/source/conf.py
trends/docs/source/index.md
trends/docs/source/installation.md
trends/docs/source/notebooks/Trends_Tutorial.ipynb
trends/py.typed
trends/trends.py
trends-0.8.2.dist-info/LICENSE
trends-0.8.2.dist-info/WHEEL
trends-0.8.2.dist-info/METADATA
trends-0.8.2.dist-info/RECORD
