Metadata-Version: 2.1
Name: trends
Version: 0.8.2
Summary: Generate and study quasi-monotonic sequences.
License: MIT
Author: Jeffrey S. Haemer
Author-email: jeffrey.haemer@gmail.com
Requires-Python: >=3.8,<4.0
Classifier: License :: OSI Approved :: MIT License
Classifier: Programming Language :: Python :: 3
Classifier: Programming Language :: Python :: 3.10
Classifier: Programming Language :: Python :: 3.8
Classifier: Programming Language :: Python :: 3.9
Provides-Extra: sphinx
Requires-Dist: pytest-mock (>=3.7.0,<4.0.0)
Requires-Dist: python-dotenv (>=0.20.0,<0.21.0)
